presentpy_jupyter/__init__.py
presentpy_jupyter/_version.py
presentpy_jupyter/handlers.py
presentpy_jupyter-0.1.7.data/data/etc/jupyter/jupyter_server_config.d/presentpy_jupyter.json
presentpy_jupyter-0.1.7.data/data/share/jupyter/labextensions/presentpy_jupyter/package.json
presentpy_jupyter-0.1.7.data/data/share/jupyter/labextensions/presentpy_jupyter/schemas/presentpy_jupyter/package.json.orig
presentpy_jupyter-0.1.7.data/data/share/jupyter/labextensions/presentpy_jupyter/schemas/presentpy_jupyter/plugin.json
presentpy_jupyter-0.1.7.data/data/share/jupyter/labextensions/presentpy_jupyter/static/509.c1762443773faef3f869.js
presentpy_jupyter-0.1.7.data/data/share/jupyter/labextensions/presentpy_jupyter/static/728.0708b0b302206c5a4ff1.js
presentpy_jupyter-0.1.7.data/data/share/jupyter/labextensions/presentpy_jupyter/static/remoteEntry.f7471bf2674f20b5b2f9.js
presentpy_jupyter-0.1.7.data/data/share/jupyter/labextensions/presentpy_jupyter/static/style.js
presentpy_jupyter-0.1.7.data/data/share/jupyter/labextensions/presentpy_jupyter/static/third-party-licenses.json
presentpy_jupyter-0.1.7.data/data/share/jupyter/labextensions/presentpy_jupyter/install.json
presentpy_jupyter-0.1.7.dist-info/METADATA
presentpy_jupyter-0.1.7.dist-info/WHEEL
presentpy_jupyter-0.1.7.dist-info/licenses/LICENSE
presentpy_jupyter-0.1.7.dist-info/RECORD
