Metadata-Version: 2.3
Name: presentpy_jupyter
Version: 0.1.7
Summary: A JupyterLab extension.
Project-URL: Homepage, https://github.com/fferegrino/presentpy-jupyter
Project-URL: Bug Tracker, https://github.com/fferegrino/presentpy-jupyter/issues
Project-URL: Repository, https://github.com/fferegrino/presentpy-jupyter
Author-email: Antonio Feregrino <antonio.feregrino@gmail.com>
License: BSD 3-Clause License
License-File: LICENSE
Keywords: jupyter,jupyterlab,jupyterlab-extension
Classifier: Framework :: Jupyter
Classifier: Framework :: Jupyter :: JupyterLab
Classifier: Framework :: Jupyter :: JupyterLab :: 4
Classifier: Framework :: Jupyter :: JupyterLab :: Extensions
Classifier: Framework :: Jupyter :: JupyterLab :: Extensions :: Prebuilt
Classifier: License :: OSI Approved :: BSD License
Classifier: Programming Language :: Python
Classifier: Programming Language :: Python :: 3
Classifier: Programming Language :: Python :: 3.8
Classifier: Programming Language :: Python :: 3.9
Classifier: Programming Language :: Python :: 3.10
Classifier: Programming Language :: Python :: 3.11
Classifier: Programming Language :: Python :: 3.12
Requires-Python: >=3.8
Requires-Dist: jupyter-server<3,>=2.0.1
Requires-Dist: presentpy
